stitchee/__init__.py
stitchee/cli.py
stitchee/concatenate.py
stitchee/file_ops.py
stitchee/harmony/__init__.py
stitchee/harmony/cli.py
stitchee/harmony/download_worker.py
stitchee/harmony/service_adapter.py
stitchee/harmony/util.py
stitchee/history_handling.py
stitchee-1.9.0.dist-info/LICENSE
stitchee-1.9.0.dist-info/METADATA
stitchee-1.9.0.dist-info/WHEEL
stitchee-1.9.0.dist-info/entry_points.txt
stitchee-1.9.0.dist-info/RECORD
