Metadata-Version: 2.3
Name: stitchee
Version: 1.9.0
Summary: NetCDF4 Along-existing-dimension Concatenation Service
License: Apache License
Author: Daniel Kaufman
Author-email: daniel.kaufman@nasa.gov
Requires-Python: >=3.12,<4
Classifier: License :: Other/Proprietary License
Classifier: Programming Language :: Python :: 3
Classifier: Programming Language :: Python :: 3.12
Classifier: Programming Language :: Python :: 3.13
Provides-Extra: dev
Provides-Extra: harmony
Provides-Extra: integration
Requires-Dist: harmony-py (>=0.4.15) ; extra == "integration"
Requires-Dist: harmony-service-lib (>=2.0.0) ; extra == "harmony"
Requires-Dist: importlib-metadata (>=8.4.0)
Requires-Dist: markdown-callouts (>=0.4.0) ; extra == "dev"
Requires-Dist: markdown-include (>=0.8.1) ; extra == "dev"
Requires-Dist: mkdocs (>=1.6.0) ; extra == "dev"
Requires-Dist: mkdocs-jupyter (>=0.24.7) ; extra == "dev"
Requires-Dist: mkdocs-material (>=9.5.22) ; extra == "dev"
Requires-Dist: mkdocstrings (>=0.25.1) ; extra == "dev"
Requires-Dist: mkdocstrings-python (>=1.16.12) ; extra == "dev"
Requires-Dist: mypy (>=1.9.0) ; extra == "dev"
Requires-Dist: netcdf4 (>=1.6.5)
Requires-Dist: pystac (>=0.5.3)
Requires-Dist: pytest (>=8.1.1) ; extra == "dev"
Requires-Dist: pytest-cov (>=5.0.0) ; extra == "dev"
Requires-Dist: ruff (>=0.5.0) ; extra == "dev"
Requires-Dist: xarray (>=2024.3.0)
Project-URL: Bug Tracker, https://github.com/nasa/stitchee/issues
Project-URL: Changelog, https://github.com/nasa/stitchee/blob/main/CHANGELOG.md
Project-URL: Documentation, https://stitchee.readthedocs.io
Project-URL: Repository, https://github.com/nasa/stitchee
